MANIFEST.in
README.rst
setup.py
pds_cdf/__init__.py
pds_cdf/cdf.py
pds_cdf.egg-info/PKG-INFO
pds_cdf.egg-info/SOURCES.txt
pds_cdf.egg-info/dependency_links.txt
pds_cdf.egg-info/not-zip-safe
pds_cdf.egg-info/requires.txt
pds_cdf.egg-info/top_level.txt