Metadata-Version: 1.0
Name: pds-cdf
Version: 0.1.3
Summary: A python CDF reader
Home-page: http://github.com/MAVENSDC/PDScdf
Author: MAVEN SDC
Author-email: mavensdc@lasp.colorado.edu
License: MIT
Keywords: tplot maven lasp idl
Platform: UNKNOWN
